teareduce/__init__.py
teareduce/avoid_astropy_warnings.py
teareduce/correct_pincushion_distortion.py
teareduce/cosmicrays.py
teareduce/ctext.py
teareduce/draw_rectangle.py
teareduce/elapsed_time.py
teareduce/histogram1d.py
teareduce/imshow.py
teareduce/numsplines.py
teareduce/peaks_spectrum.py
teareduce/polfit.py
teareduce/robust_std.py
teareduce/sdistortion.py
teareduce/simulateccdexposure.py
teareduce/sliceregion.py
teareduce/statsummary.py
teareduce/version.py
teareduce/wavecal.py
teareduce/write_array_to_fits.py
teareduce/zscale.py
teareduce/cleanest/__init__.py
teareduce/cleanest/__main__.py
teareduce/cleanest/askextension.py
teareduce/cleanest/centerchildparent.py
teareduce/cleanest/cosmicraycleanerapp.py
teareduce/cleanest/definitions.py
teareduce/cleanest/dilatemask.py
teareduce/cleanest/find_closest_true.py
teareduce/cleanest/gausskernel2d_elliptical.py
teareduce/cleanest/imagedisplay.py
teareduce/cleanest/interpolate.py
teareduce/cleanest/interpolation_a.py
teareduce/cleanest/interpolation_x.py
teareduce/cleanest/interpolation_y.py
teareduce/cleanest/interpolationeditor.py
teareduce/cleanest/lacosmicpad.py
teareduce/cleanest/mergemasks.py
teareduce/cleanest/modalprogressbar.py
teareduce/cleanest/parametereditor.py
teareduce/cleanest/reviewcosmicray.py
teareduce/cleanest/trackedbutton.py
teareduce/cookbook/__init__.py
teareduce/cookbook/get_cookbook_file.py
teareduce/tests/__init__.py
teareduce/tests/test_cleanest.py
teareduce/tests/test_sliceregion.py
teareduce/tests/test_version.py
teareduce-0.6.8.dist-info/licenses/LICENSE.txt
teareduce-0.6.8.dist-info/METADATA
teareduce-0.6.8.dist-info/WHEEL
teareduce-0.6.8.dist-info/entry_points.txt
teareduce-0.6.8.dist-info/top_level.txt
teareduce-0.6.8.dist-info/RECORD
