Metadata-Version: 2.4
Name: teareduce
Version: 0.6.8
Summary: Utilities for astronomical data reduction
Author-email: Nicolás Cardiel <cardiel@ucm.es>
License: GPL-3.0-or-later
Project-URL: Homepage, https://github.com/nicocardiel/teareduce
Project-URL: Repository, https://github.com/nicocardiel/teareduce.git
Classifier: Programming Language :: Python :: 3.10
Classifier: Programming Language :: Python :: 3.11
Classifier: Programming Language :: Python :: 3.12
Classifier: Programming Language :: Python :: 3.13
Classifier: Development Status :: 3 - Alpha
Classifier: Environment :: Console
Classifier: Intended Audience :: Science/Research
Classifier: License :: OSI Approved :: GNU General Public License v3 (GPLv3)
Classifier: Operating System :: OS Independent
Classifier: Topic :: Scientific/Engineering :: Astronomy
Requires-Python: >=3.10
License-File: LICENSE.txt
Requires-Dist: astropy
Requires-Dist: lmfit
Requires-Dist: matplotlib
Requires-Dist: numpy>=2
Requires-Dist: requests
Requires-Dist: rich
Requires-Dist: rich-argparse
Requires-Dist: scipy
Requires-Dist: tqdm
Provides-Extra: cleanest
Requires-Dist: ccdproc; extra == "cleanest"
Requires-Dist: cosmic-conn; extra == "cleanest"
Requires-Dist: deepCR; extra == "cleanest"
Requires-Dist: maskfill; extra == "cleanest"
Provides-Extra: test
Requires-Dist: pytest; extra == "test"
Dynamic: license-file
